python_zephyr-0.0.15.data/scripts/tc_report_upload.py
zephyr/__init__.py
zephyr/exceptions.py
zephyr/filecache.py
zephyr/interface.py
zephyr/tc_mgmt.py
python_zephyr-0.0.15.dist-info/LICENSE.txt
python_zephyr-0.0.15.dist-info/METADATA
python_zephyr-0.0.15.dist-info/WHEEL
python_zephyr-0.0.15.dist-info/top_level.txt
python_zephyr-0.0.15.dist-info/RECORD
