Metadata-Version: 2.1
Name: python-zephyr
Version: 0.0.15
Summary: An easy to use Zephyr Scale library for python
Home-page: https://bitbucket.org/melectrification/python-zephyr/src/master/
Author: Atabey Onur
Author-email: a.onur@munichelectrification.com
Maintainer: Atabey Onur
Maintainer-email: a.onur@munichelectrification.com
Classifier: Programming Language :: Python :: 3
Classifier: License :: OSI Approved :: MIT License
Classifier: Operating System :: OS Independent
Requires-Python: >=3.6
License-File: LICENSE.txt
Requires-Dist: requests
